tracelogger/__init__.py
tracelogger/tracelogger.py
tracelogger-0.1.3.dist-info/LICENSE
tracelogger-0.1.3.dist-info/METADATA
tracelogger-0.1.3.dist-info/WHEEL
tracelogger-0.1.3.dist-info/RECORD
