Metadata-Version: 2.1
Name: tracelogger
Version: 0.1.3
Summary: Print each local variable and line of code at execution
Home-page: https://github.com/xLaszlo/tracelogger
License: MIT
Author: Laszlo Sragner
Author-email: sragner@gmail.com
Requires-Python: >=3.9,<4.0
Classifier: License :: OSI Approved :: MIT License
Classifier: Programming Language :: Python :: 3
Classifier: Programming Language :: Python :: 3.9
Classifier: Programming Language :: Python :: 3.10
Classifier: Programming Language :: Python :: 3.11
Project-URL: Documentation, https://github.com/xLaszlo/tracelogger
